README.rst
setup.py
django_googleauth.egg-info/PKG-INFO
django_googleauth.egg-info/SOURCES.txt
django_googleauth.egg-info/dependency_links.txt
django_googleauth.egg-info/requires.txt
django_googleauth.egg-info/top_level.txt
googleauth/__init__.py
googleauth/backends.py
googleauth/models.py
googleauth/urls.py
googleauth/views.py