Metadata-Version: 1.1
Name: django-googleauth
Version: 2.1
Summary: OAuth 2.0 authentication for Google and Google Apps accounts
Home-page: https://github.com/jcarbaugh/django-googleauth
Author: Jeremy Carbaugh
Author-email: jcarbaugh@gmail.com
License: BSD
Platform: any
Classifier: Development Status :: 4 - Beta
Classifier: Intended Audience :: Developers
Classifier: License :: OSI Approved :: BSD License
Classifier: Natural Language :: English
Classifier: Operating System :: OS Independent
Classifier: Programming Language :: Python
Classifier: Topic :: Software Development :: Libraries :: Python Modules
